neural_network_from_scratch/__init__.py
neural_network_from_scratch/_modidx.py
neural_network_from_scratch/activation.py
neural_network_from_scratch/core.py
neural_network_from_scratch-0.0.1.dist-info/LICENSE
neural_network_from_scratch-0.0.1.dist-info/METADATA
neural_network_from_scratch-0.0.1.dist-info/WHEEL
neural_network_from_scratch-0.0.1.dist-info/entry_points.txt
neural_network_from_scratch-0.0.1.dist-info/top_level.txt
neural_network_from_scratch-0.0.1.dist-info/RECORD
